{
  "1":  { "name": "User1",  "points": 0, "rank": 1, "achievements": [], "tasks_solved": 0 },
  "2":  { "name": "User2",  "points": 0, "rank": 1, "achievements": [], "tasks_solved": 0 },
  "3":  { "name": "User3",  "points": 0, "rank": 1, "achievements": [], "tasks_solved": 0 },
  "4":  { "name": "User4",  "points": 0, "rank": 1, "achievements": [], "tasks_solved": 0 },
  "5":  { "name": "User5",  "points": 0, "rank": 1, "achievements": [], "tasks_solved": 0 },
  "6":  { "name": "User6",  "points": 0, "rank": 1, "achievements": [], "tasks_solved": 0 },
  "7":  { "name": "User7",  "points": 0, "rank": 1, "achievements": [], "tasks_solved": 0 },
  "8":  { "name": "User8",  "points": 0, "rank": 1, "achievements": [], "tasks_solved": 0 },
  "9":  { "name": "User9",  "points": 0, "rank": 1, "achievements": [], "tasks_solved": 0 },
  "10": { "name": "User10", "points": 0, "rank": 1, "achievements": [], "tasks_solved": 0 },
  "11": { "name": "User11", "points": 0, "rank": 1, "achievements": [], "tasks_solved": 0 },
  "12": { "name": "User12", "points": 0, "rank": 1, "achievements": [], "tasks_solved": 0 },
  "13": { "name": "User13", "points": 0, "rank": 1, "achievements": [], "tasks_solved": 0 },
  "14": { "name": "User14", "points": 0, "rank": 1, "achievements": [], "tasks_solved": 0 },
  "15": { "name": "User15", "points": 0, "rank": 1, "achievements": [], "tasks_solved": 0 },
  "16": { "name": "User16", "points": 0, "rank": 1, "achievements": [], "tasks_solved": 0 },
  "17": { "name": "User17", "points": 0, "rank": 1, "achievements": [], "tasks_solved": 0 },
  "18": { "name": "User18", "points": 0, "rank": 1, "achievements": [], "tasks_solved": 0 },
  "19": { "name": "User19", "points": 0, "rank": 1, "achievements": [], "tasks_solved": 0 },
  "20": { "name": "User20", "points": 0, "rank": 1, "achievements": [], "tasks_solved": 0 },
  "21": { "name": "User21", "points": 0, "rank": 1, "achievements": [], "tasks_solved": 0 },
  "22": { "name": "User22", "points": 0, "rank": 1, "achievements": [], "tasks_solved": 0 },
  "23": { "name": "User23", "points": 0, "rank": 1, "achievements": [], "tasks_solved": 0 },
  "24": { "name": "User24", "points": 0, "rank": 1, "achievements": [], "tasks_solved": 0 },
  "25": { "name": "User25", "points": 0, "rank": 1, "achievements": [], "tasks_solved": 0 },
  "26": { "name": "User26", "points": 0, "rank": 1, "achievements": [], "tasks_solved": 0 },
  "27": { "name": "User27", "points": 0, "rank": 1, "achievements": [], "tasks_solved": 0 },
  "28": { "name": "User28", "points": 0, "rank": 1, "achievements": [], "tasks_solved": 0 },
  "29": { "name": "User29", "points": 0, "rank": 1, "achievements": [], "tasks_solved": 0 },
  "30": { "name": "User30", "points": 0, "rank": 1, "achievements": [], "tasks_solved": 0 },
  "31": { "name": "User31", "points": 0, "rank": 1, "achievements": [], "tasks_solved": 0 },
  "32": { "name": "User32", "points": 0, "rank": 1, "achievements": [], "tasks_solved": 0 },
  "33": { "name": "User33", "points": 0, "rank": 1, "achievements": [], "tasks_solved": 0 },
  "34": { "name": "User34", "points": 0, "rank": 1, "achievements": [], "tasks_solved": 0 },
  "35": { "name": "User35", "points": 0, "rank": 1, "achievements": [], "tasks_solved": 0 },
  "36": { "name": "User36", "points": 0, "rank": 1, "achievements": [], "tasks_solved": 0 },
  "37": { "name": "User37", "points": 0, "rank": 1, "achievements": [], "tasks_solved": 0 },
  "38": { "name": "User38", "points": 0, "rank": 1, "achievements": [], "tasks_solved": 0 },
  "39": { "name": "User39", "points": 0, "rank": 1, "achievements": [], "tasks_solved": 0 },
  "40": { "name": "User40", "points": 0, "rank": 1, "achievements": [], "tasks_solved": 0 },
  "41": { "name": "User41", "points": 0, "rank": 1, "achievements": [], "tasks_solved": 0 },
  "42": { "name": "User42", "points": 0, "rank": 1, "achievements": [], "tasks_solved": 0 },
  "43": { "name": "User43", "points": 0, "rank": 1, "achievements": [], "tasks_solved": 0 },
  "44": { "name": "User44", "points": 0, "rank": 1, "achievements": [], "tasks_solved": 0 },
  "45": { "name": "User45", "points": 0, "rank": 1, "achievements": [], "tasks_solved": 0 },
  "46": { "name": "User46", "points": 0, "rank": 1, "achievements": [], "tasks_solved": 0 },
  "47": { "name": "User47", "points": 0, "rank": 1, "achievements": [], "tasks_solved": 0 },
  "48": { "name": "User48", "points": 0, "rank": 1, "achievements": [], "tasks_solved": 0 },
  "49": { "name": "User49", "points": 0, "rank": 1, "achievements": [], "tasks_solved": 0 },
  "50": { "name": "User50", "points": 0, "rank": 1, "achievements": [], "tasks_solved": 0 },
  "51": { "name": "User51", "points": 0, "rank": 1, "achievements": [], "tasks_solved": 0 },
  "52": { "name": "User52", "points": 0, "rank": 1, "achievements": [], "tasks_solved": 0 },
  "53": { "name": "User53", "points": 0, "rank": 1, "achievements": [], "tasks_solved": 0 },
  "54": { "name": "User54", "points": 0, "rank": 1, "achievements": [], "tasks_solved": 0 },
  "55": { "name": "User55", "points": 0, "rank": 1, "achievements": [], "tasks_solved": 0 },
  "56": { "name": "User56", "points": 0, "rank": 1, "achievements": [], "tasks_solved": 0 },
  "57": { "name": "User57", "points": 0, "rank": 1, "achievements": [], "tasks_solved": 0 },
  "58": { "name": "User58", "points": 0, "rank": 1, "achievements": [], "tasks_solved": 0 },
  "59": { "name": "User59", "points": 0, "rank": 1, "achievements": [], "tasks_solved": 0 },
  "60": { "name": "User60", "points": 0, "rank": 1, "achievements": [], "tasks_solved": 0 }
}
